redirect_streams/__init__.py
redirect_streams-0.1.0.dist-info/DESCRIPTION.rst
redirect_streams-0.1.0.dist-info/METADATA
redirect_streams-0.1.0.dist-info/metadata.json
redirect_streams-0.1.0.dist-info/pbr.json
redirect_streams-0.1.0.dist-info/RECORD
redirect_streams-0.1.0.dist-info/top_level.txt
redirect_streams-0.1.0.dist-info/WHEEL
