Metadata-Version: 2.0
Name: redirect-streams
Version: 0.1.0
Summary: Easy stream redirection in Python.
Home-page: https://github.com/jambonrose/redirect_streams
Author: Andrew Pinkham
Author-email: hello at andrewsforge dot com
License: Simplified BSD License
Keywords: stream,stdout,stderr,with,context managers
Platform: UNKNOWN
Classifier: Development Status :: 1 - Planning
Classifier: Intended Audience :: Developers
Classifier: Topic :: Software Development :: Libraries :: Python Modules
Classifier: License :: OSI Approved :: BSD License
Classifier: Operating System :: OS Independent
Classifier: Programming Language :: Python :: 2
Classifier: Programming Language :: Python :: 2.6
Classifier: Programming Language :: Python :: 2.7
Classifier: Programming Language :: Python :: 3
Classifier: Programming Language :: Python :: 3.2
Classifier: Programming Language :: Python :: 3.3
Classifier: Programming Language :: Python :: 3.4
